qrusty_pyclient.py
qrusty_pyclient-0.4.0.dist-info/METADATA
qrusty_pyclient-0.4.0.dist-info/WHEEL
qrusty_pyclient-0.4.0.dist-info/top_level.txt
qrusty_pyclient-0.4.0.dist-info/RECORD
