Metadata-Version: 2.4
Name: qrusty_pyclient
Version: 0.4.0
Summary: Python client wrapper for the qrusty API.
Author-email: Gordon Greene <greeng3@obscure-reference.com>
License-Expression: MIT
Requires-Python: >=3.7
Requires-Dist: requests
